ixlab_sshui-1.0.0.dist-info/licenses/LICENSE
sshui/__init__.py
sshui/about_dialog.py
sshui/main_window.py
sshui/option_dialog.py
sshui/tag_dialog.py
sshui/text_prompt_dialog.py
ixlab_sshui-1.0.0.dist-info/METADATA
ixlab_sshui-1.0.0.dist-info/WHEEL
ixlab_sshui-1.0.0.dist-info/entry_points.txt
ixlab_sshui-1.0.0.dist-info/top_level.txt
ixlab_sshui-1.0.0.dist-info/RECORD
