Metadata-Version: 2.4
Name: ixlab-sshui
Version: 1.0.0
Summary: PyQt6 UI for browsing and tagging SSH configs via sshcore.
Author-email: Iacopo Palazzi <iacopo.palazzi@gmail.com>
License: MIT
Project-URL: Homepage, https://github.com/iakko/sshui
Keywords: ssh,ui,pyqt,config
Requires-Python: >=3.10
License-File: LICENSE
Requires-Dist: ixlab-sshcore>=1.0.0
Requires-Dist: PyQt6>=6.5
Dynamic: license-file
